README.rst
setup.cfg
setup.py
runtime_typecheck/__init__.py
runtime_typecheck/runtime_typecheck.py
runtime_typecheck.egg-info/PKG-INFO
runtime_typecheck.egg-info/SOURCES.txt
runtime_typecheck.egg-info/dependency_links.txt
runtime_typecheck.egg-info/top_level.txt