Metadata-Version: 1.1
Name: runtime-typecheck
Version: 0.7
Summary: Runtime type checking with Python 3.6 typing
Home-page: https://github.com/jacopofar/runtime_typecheck
Author: Jacopo Farina
Author-email: jacopo1.farina@gmail.com
License: MIT
Download-URL: https://github.com/jacopofar/runtime_typecheck/archive/0.2.tar.gz
Platform: UNKNOWN
